{
  "extension.displayName": "ini Theme",
  "extension.description": "Le thème officiel pour ini.so",
  "config.title": "ini Theme",
  "config.italicComments": "Utiliser l'italique pour les commentaires.",
  "config.italicKeywords": "Utiliser l'italique pour les mots-clés.",
  "config.boldKeywords": "Utiliser le gras pour les mots-clés.",
  "config.neutralScale": "Sélectionner l'échelle de couleurs neutres (affecte l'arrière-plan et l'atmosphère générale).",
  "config.primaryScale": "Sélectionner la couleur d'accentuation principale (affecte les points forts et le curseur).",
  "command.regenerate": "ini: Régénérer le thème",
  "command.setDark": "ini: Définir le thème sombre",
  "command.setLight": "ini: Définir le thème clair",
  "command.setPrimaryScale": "ini: Définir la couleur primaire",
  "command.setNeutralScale": "ini: Définir la couleur neutre"
}
